AlgoMarker/AlgoMarker.py
AlgoMarker/__init__.py
med/__init__.py
med/_medpython.so
med/med.py
med/medpython.py
medpython.libs/libgomp-a34b3233.so.1.0.0
medpython-1.1.1.dist-info/METADATA
medpython-1.1.1.dist-info/WHEEL
medpython-1.1.1.dist-info/top_level.txt
medpython-1.1.1.dist-info/RECORD
medpython-1.1.1.dist-info/licenses/LICENCE
medpython-1.1.1.dist-info/sboms/auditwheel.cdx.json
