Metadata-Version: 2.4
Name: medpython
Version: 1.1.1
Summary: Medial EarlySign Python
Author: Alon Lanyado
License-Expression: MIT
Project-URL: Homepage, https://github.com/Medial-EarlySign/medpython
Project-URL: Repository, https://github.com/Medial-EarlySign/medpython
Project-URL: Documentation, https://medial-earlysign.github.io/MR_Wiki/
Project-URL: Changelog, https://github.com/Medial-EarlySign/medpython/discussions/categories/announcements
Keywords: EMR,EHR,machine-learning,medicine,time-series,clinical,healthcare,clinical-data,medical,clinical-data-warehouse,tabular-data
Classifier: Programming Language :: Python :: 3
Classifier: Programming Language :: C++
Classifier: Programming Language :: C
Classifier: Operating System :: POSIX :: Linux
Classifier: Operating System :: MacOS
Classifier: Operating System :: Microsoft :: Windows
Classifier: Topic :: Scientific/Engineering
Classifier: Topic :: Scientific/Engineering :: Artificial Intelligence
Classifier: Topic :: Software Development :: Libraries
Requires-Python: >=3.8
License-File: LICENCE
Requires-Dist: numpy>=1.21.0
Requires-Dist: pandas
Requires-Dist: plotly
Requires-Dist: medpython-etl>=1.0.2
Dynamic: license-file
